Metadata-Version: 2.1
Name: wanwu-sentry-dingtalk
Version: 0.0.5
Summary: Sentry DingTalk Robot
Home-page: https://code.aliyun.com/PlayGoods-Materiel/wanwu-senstry-dingtalk.git
Author: dazao
Author-email: zhaodazao@gmail.com
License: BSD
Keywords: wanwu-sentry-dingtalk
Platform: any
Classifier: Framework :: Django
Classifier: Intended Audience :: Developers
Classifier: Intended Audience :: System Administrators
Classifier: Operating System :: OS Independent
Classifier: Topic :: Software Development
Provides-Extra: test
